cmomy/__init__.py
cmomy/__init__.pyi
cmomy/_concat.py
cmomy/_lib/__init__.py
cmomy/_lib/_binomial.py
cmomy/_lib/_push.py
cmomy/_lib/_push_cov.py
cmomy/_lib/_rolling.py
cmomy/_lib/_rolling_cov.py
cmomy/_lib/convert.py
cmomy/_lib/convert_cov.py
cmomy/_lib/decorators.py
cmomy/_lib/grouped.py
cmomy/_lib/grouped_cov.py
cmomy/_lib/grouped_cov_parallel.py
cmomy/_lib/grouped_parallel.py
cmomy/_lib/push.py
cmomy/_lib/push_cov.py
cmomy/_lib/push_cov_parallel.py
cmomy/_lib/push_parallel.py
cmomy/_lib/resample.py
cmomy/_lib/resample_cov.py
cmomy/_lib/resample_cov_parallel.py
cmomy/_lib/resample_parallel.py
cmomy/_lib/rolling.py
cmomy/_lib/rolling_cov.py
cmomy/_lib/rolling_cov_parallel.py
cmomy/_lib/rolling_parallel.py
cmomy/_lib/utils.py
cmomy/compile.py
cmomy/confidence_interval.py
cmomy/convert.py
cmomy/core/__init__.py
cmomy/core/_typing_kwargs.py
cmomy/core/array_utils.py
cmomy/core/compat.py
cmomy/core/docstrings.py
cmomy/core/formatting.py
cmomy/core/missing.py
cmomy/core/moment_params.py
cmomy/core/prepare.py
cmomy/core/prob.py
cmomy/core/typing.py
cmomy/core/typing_compat.py
cmomy/core/typing_nested_sequence.py
cmomy/core/utils.py
cmomy/core/validate.py
cmomy/core/xr_utils.py
cmomy/factory.py
cmomy/grouped/__init__.py
cmomy/grouped/_factorize.py
cmomy/grouped/_grouper.py
cmomy/grouped/_reduction.py
cmomy/options.py
cmomy/py.typed
cmomy/random.py
cmomy/reduction.py
cmomy/resample/__init__.py
cmomy/resample/__init__.pyi
cmomy/resample/_factory_sampler.py
cmomy/resample/_resample.py
cmomy/resample/_sampler.py
cmomy/resample/_typing_kwargs.py
cmomy/resample/_utils.py
cmomy/resample/typing.py
cmomy/rolling.py
cmomy/utils.py
cmomy/wrapper/__init__.py
cmomy/wrapper/_constructors.py
cmomy/wrapper/_wrapper.py
cmomy/wrapper/_wrapper_abc.py
cmomy/wrapper/typing.py
cmomy-1.0.3.dist-info/licenses/LICENSE
cmomy-1.0.3.dist-info/WHEEL
cmomy-1.0.3.dist-info/METADATA
cmomy-1.0.3.dist-info/RECORD
