Metadata-Version: 2.4
Name: cmomy
Version: 1.0.3
Summary: Central (co)moment calculation/manipulation
Keywords: cmomy
Author: William P. Krekelberg
Author-email: William P. Krekelberg <wpk@nist.gov>
License-Expression: NIST-PD
License-File: LICENSE
Classifier: Development Status :: 2 - Pre-Alpha
Classifier: Intended Audience :: Science/Research
Classifier: Operating System :: OS Independent
Classifier: Programming Language :: Python
Classifier: Programming Language :: Python :: 3 :: Only
Classifier: Programming Language :: Python :: 3.10
Classifier: Programming Language :: Python :: 3.11
Classifier: Programming Language :: Python :: 3.12
Classifier: Programming Language :: Python :: 3.13
Classifier: Programming Language :: Python :: 3.14
Classifier: Topic :: Scientific/Engineering
Requires-Dist: docstring-inheritance
Requires-Dist: lazy-loader
Requires-Dist: module-utilities>=0.10.1
Requires-Dist: numba>=0.58,<0.63 ; python_full_version < '3.14' and platform_machine == 'x86_64' and sys_platform == 'darwin'
Requires-Dist: numba>=0.58 ; (python_full_version < '3.14' and sys_platform != 'darwin') or platform_machine != 'x86_64'
Requires-Dist: numba>=0.63 ; python_full_version >= '3.14'
Requires-Dist: numpy>1.24
Requires-Dist: typing-extensions>=4.10.0
Requires-Dist: xarray>=2023.9.0
Requires-Python: >=3.10
Project-URL: Documentation, https://pages.nist.gov/cmomy/
Project-URL: Homepage, https://github.com/usnistgov/cmomy
